nmail/__init__.py
nmail-0.0.3.dist-info/LICENSE
nmail-0.0.3.dist-info/METADATA
nmail-0.0.3.dist-info/WHEEL
nmail-0.0.3.dist-info/top_level.txt
nmail-0.0.3.dist-info/RECORD
