Metadata-Version: 2.1
Name: nmail
Version: 0.0.3
Summary: One-line SMPT email sender
Home-page: https://github.com/solry/nmail
Author: Roman Solyanik
Author-email: solyanikry@gmail.com
License: UNKNOWN
Platform: UNKNOWN
Classifier: Programming Language :: Python :: 3
Classifier: License :: OSI Approved :: MIT License
Classifier: Operating System :: OS Independent
